{
  "required": true,
  "minVersion": "0.8",
  "package": "de.mc8051.clientenhancements.mixin",
  "compatibilityLevel": "JAVA_17",
  "mixins": [
  ],
  "client": [
    "AmbientMixin",
    "BarrierMixin",
    "BlockMixin",
    "BlockSodiumMixin",
    "BrightnessMixin",
    "CapeElytraFeatureMixin",
    "CapePlayerListMixin",
    "EntityInvoker",
    "InvisibleMixin",
    "OptionButtonMixin",
    "PacketOutputMixin",
    "SpectatorMixin",
    "ZoomMixin"
  ],
  "injectors": {
    "defaultRequire": 1
  }
}
